pymod112/RegionCode_20
pymod112/RegionCode_24
pymod112/__init__.py
pymod112/mod112.py
pymod112-0.1.5.dist-info/licenses/LICENSE
pymod112-0.1.5.dist-info/METADATA
pymod112-0.1.5.dist-info/WHEEL
pymod112-0.1.5.dist-info/top_level.txt
pymod112-0.1.5.dist-info/RECORD
