Metadata-Version: 2.4
Name: pymod112
Version: 0.1.5
Summary: 一个可以离线检验公民身份号码是否合法的程序
Author-email: HoshsL <HoshsL@outlook.com>
License-Expression: MIT
Project-URL: Homepage, https://github.com/HoshsL/PyMOD11-2
Project-URL: Bug Tracker, https://github.com/HoshsL/PyMOD11-2/issues
Keywords: mod112,mod11-2
Classifier: Programming Language :: Python :: 3
Classifier: Operating System :: OS Independent
Requires-Python: >=3.10
License-File: LICENSE
Dynamic: license-file
